fluidimage/__init__.py
fluidimage/_opencv.py
fluidimage/_version.py
fluidimage/bos.py
fluidimage/config.py
fluidimage/conftest.py
fluidimage/image2image.py
fluidimage/optical_flow.py
fluidimage/piv.py
fluidimage/preproc.py
fluidimage/run_from_xml.py
fluidimage/synthetic.py
fluidimage/test_image2image.py
fluidimage/test_run_from_xml.py
fluidimage/uvmat.py
fluidimage/calcul/__init__.py
fluidimage/calcul/correl.py
fluidimage/calcul/correl_pycuda.py
fluidimage/calcul/errors.py
fluidimage/calcul/fft.py
fluidimage/calcul/mean_neighbors.py
fluidimage/calcul/subpix.py
fluidimage/calcul/test_correl.py
fluidimage/calcul/test_fft.py
fluidimage/calcul/__numba__/correl.py
fluidimage/calcul/__numba__/fft.py
fluidimage/calcul/__numba__/mean_neighbors.py
fluidimage/calcul/__numba__/subpix.py
fluidimage/calcul/__python__/correl.py
fluidimage/calcul/__python__/fft.py
fluidimage/calcul/__python__/mean_neighbors.py
fluidimage/calcul/__python__/subpix.py
fluidimage/calcul/__pythran__/correl.cpython-312-aarch64-linux-gnu.so
fluidimage/calcul/__pythran__/fft.cpython-312-aarch64-linux-gnu.so
fluidimage/calcul/__pythran__/mean_neighbors.cpython-312-aarch64-linux-gnu.so
fluidimage/calcul/__pythran__/subpix.cpython-312-aarch64-linux-gnu.so
fluidimage/calcul/interpolate/__init__.py
fluidimage/calcul/interpolate/griddata.py
fluidimage/calcul/interpolate/test_thin_plate_spline.py
fluidimage/calcul/interpolate/thin_plate_spline.py
fluidimage/calcul/interpolate/thin_plate_spline_subdom.py
fluidimage/calcul/interpolate/__numba__/thin_plate_spline.py
fluidimage/calcul/interpolate/__python__/thin_plate_spline.py
fluidimage/calcul/interpolate/__pythran__/thin_plate_spline.cpython-312-aarch64-linux-gnu.so
fluidimage/calibration/__init__.py
fluidimage/calibration/calib2d_simple.py
fluidimage/calibration/calib_cv.py
fluidimage/calibration/calib_direct.py
fluidimage/calibration/calib_tsai.py
fluidimage/calibration/test_calib_cv.py
fluidimage-0.5.5.dist-info/METADATA
fluidimage-0.5.5.dist-info/WHEEL
fluidimage-0.5.5.dist-info/entry_points.txt
fluidimage-0.5.5.dist-info/RECORD
fluidimage-0.5.5.dist-info/licenses/LICENSE.txt
