Metadata-Version: 2.4
Name: fluidimage
Version: 0.5.5
Summary: Fluid image processing with Python.
Keywords: PIV
Author-Email: Pierre Augier <pierre.augier@legi.cnrs.fr>
License-Expression: BSD-3-Clause
License-File: LICENSE.txt
Classifier: Development Status :: 5 - Production/Stable
Classifier: Intended Audience :: Education
Classifier: Intended Audience :: Science/Research
Classifier: Programming Language :: Python
Classifier: Programming Language :: Python :: 3
Classifier: Programming Language :: Python :: 3.11
Classifier: Programming Language :: Python :: 3.12
Classifier: Programming Language :: Python :: 3.13
Classifier: Topic :: Scientific/Engineering
Project-URL: homepage, https://foss.heptapod.net/fluiddyn/fluidimage
Project-URL: documentation, https://fluidimage.readthedocs.io
Project-URL: read-only-mirror, https://github.com/fluiddyn/fluidimage
Requires-Python: >=3.11
Requires-Dist: numpy>=1.23
Requires-Dist: matplotlib>=3.6
Requires-Dist: scipy>=1.10
Requires-Dist: h5py
Requires-Dist: h5netcdf
Requires-Dist: transonic>=0.6.2
Requires-Dist: fluiddyn>=0.6.2
Requires-Dist: pyfftw>=0.14
Requires-Dist: imageio
Requires-Dist: scikit-image>=0.20
Requires-Dist: trio>=0.26
Requires-Dist: dask[array]
Requires-Dist: ipython
Requires-Dist: rich>=13.7.1
Requires-Dist: textual
Provides-Extra: pims
Requires-Dist: pims; extra == "pims"
Provides-Extra: opencv
Requires-Dist: opencv-python; extra == "opencv"
Provides-Extra: graph
Requires-Dist: gprof2dot; extra == "graph"
Provides-Extra: test
Requires-Dist: pytest; extra == "test"
Requires-Dist: pytest-asyncio; extra == "test"
Provides-Extra: all
Requires-Dist: fluidimage[graph,opencv,pims,test]; extra == "all"
